gpuselect/__init__.py
gpuselect/nvmlgpuselect.py
gpuselect-0.1.4.dist-info/METADATA
gpuselect-0.1.4.dist-info/WHEEL
gpuselect-0.1.4.dist-info/entry_points.txt
gpuselect-0.1.4.dist-info/top_level.txt
gpuselect-0.1.4.dist-info/RECORD
