Metadata-Version: 2.4
Name: gpuselect
Version: 0.1.4
Summary: A simple tool for selecting available GPUs on multi-GPU servers
Project-URL: Homepage, https://github.com/grill-lab/gpuselect
Requires-Python: >=3.10
Requires-Dist: nvidia-ml-py==12.560.30
Provides-Extra: test
Requires-Dist: pytest==8.3.3; extra == "test"
